codycd-0.2.0.dist-info/RECORD
codycd-0.2.0.dist-info/metadata.json
codycd-0.2.0.dist-info/WHEEL
codycd-0.2.0.dist-info/entry_points.txt
codycd-0.2.0.dist-info/DESCRIPTION.rst
codycd-0.2.0.dist-info/top_level.txt
codycd-0.2.0.dist-info/METADATA
cody/tasks.py
cody/config.py
cody/__init__.py
cody/main.py
cody/shell/shell.py
cody/shell/__init__.py
cody/api/__init__.py
cody/api/routes.py
