Metadata-Version: 2.0
Name: codycd
Version: 0.2.0
Summary: Cody is a lightweight microservice that you can install on your machines to automate deploy requests with a simple POST request using Gitlab!
Home-page: https://github.com/lotrekagency/cody
Author: Lotrèk
Author-email: dimmitutto@lotrek.it
License: MIT
Platform: UNKNOWN
Classifier: Environment :: Web Environment
Classifier: Intended Audience :: Developers
Classifier: Programming Language :: Python
Classifier: Programming Language :: Python :: 3
Requires-Dist: bottle (==0.12.17)
Requires-Dist: gunicorn (==19.9.0)
Requires-Dist: python-daemon
Requires-Dist: lockfile
Requires-Dist: huey (==2.1.2)
Requires-Dist: requests (==2.22.0)
